metamaterialanalysiscode/__init__.py
metamaterialanalysiscode/_modules/__init__.py
metamaterialanalysiscode/_modules/_centers_RPA.py
metamaterialanalysiscode/classes/MACAnalysis.py
metamaterialanalysiscode/classes/MACCell.py
metamaterialanalysiscode/classes/MACElement.py
metamaterialanalysiscode/classes/MACGlobals.py
metamaterialanalysiscode/classes/MACLoadCase.py
metamaterialanalysiscode/classes/MACMaterial.py
metamaterialanalysiscode/classes/MACModel.py
metamaterialanalysiscode/classes/MACNode.py
metamaterialanalysiscode/classes/MACNonLinear.py
metamaterialanalysiscode/classes/MACProperty.py
metamaterialanalysiscode/classes/MACStructure.py
metamaterialanalysiscode/classes/MACSubcase.py
metamaterialanalysiscode/classes/MACTable.py
metamaterialanalysiscode/classes/__init__.py
metamaterialanalysiscode/modules/MACRun.py
metamaterialanalysiscode/modules/__init__.py
metamaterialanalysiscode-1.0.dist-info/LICENSE
metamaterialanalysiscode-1.0.dist-info/METADATA
metamaterialanalysiscode-1.0.dist-info/WHEEL
metamaterialanalysiscode-1.0.dist-info/top_level.txt
metamaterialanalysiscode-1.0.dist-info/RECORD
