Metadata-Version: 2.1
Name: metamaterialanalysiscode
Version: 1.0
Summary: Package that cretaes metamaterial FEM models
Author-email: Manuel Sánchez García <msg.aerospace@gmail.com>
License: Copyright 2023 Manuel Sánchez García
Project-URL: ETSIAE, https://www.etsiae.upm.es/
Project-URL: LinkedIn, https://www.linkedin.com/in/manuel-s%C3%A1nchez-garc%C3%ADa-8aa683232/
Project-URL: GitHub, https://github.com/ManuelSG96/MAC
Keywords: MAC,Preprocessing,Metamaterial,FEM
Classifier: Intended Audience :: Science/Research
Classifier: Programming Language :: Python :: 3.11
Classifier: License :: OSI Approved :: MIT License
Classifier: Operating System :: OS Independent
Classifier: Topic :: Scientific/Engineering
Requires-Python: >=3.10
License-File: LICENSE
Requires-Dist: numpy (>=1.24.0)
